LICENSE
README.md
setup.cfg
setup.py
mpp/__init__.py
mpp/constants.py
mpp/profile.py
mpp/blocks/__init__.py
mpp/blocks/block.py
mpp/options/__init__.py
mpp/options/option.py
mpp/parser/__init__.py
mpp/parser/parser.py
mpp/statements/__init__.py
mpp/statements/statement.py
pyMalleableProfileParser.egg-info/PKG-INFO
pyMalleableProfileParser.egg-info/SOURCES.txt
pyMalleableProfileParser.egg-info/dependency_links.txt
pyMalleableProfileParser.egg-info/top_level.txt