Metadata-Version: 2.1
Name: pyMalleableProfileParser
Version: 0.3.3
Summary: Parses Cobalt Strike malleable C2 profiles
Home-page: https://github.com/brett-fitz/pyMalleableProfileParser
Author: Brett Fitzpatrick
License: MIT
Keywords: cobalt strike,malleable profile,parser
Classifier: Development Status :: 4 - Beta
Classifier: Programming Language :: Python :: 3.5
Classifier: Programming Language :: Python :: 3.6
Classifier: Programming Language :: Python :: 3.7
Classifier: Programming Language :: Python :: 3.8
Classifier: Programming Language :: Python :: 3.9
Requires-Python: ~=3.5
License-File: LICENSE
